contracts_hj3415/__init__.py
contracts_hj3415/nfs/__init__.py
contracts_hj3415/nfs/c101_dto.py
contracts_hj3415/nfs/c103_dto.py
contracts_hj3415/nfs/c104_dto.py
contracts_hj3415/nfs/c106_dto.py
contracts_hj3415/nfs/c108_dto.py
contracts_hj3415/nfs/constants.py
contracts_hj3415/nfs/nfs_dto.py
contracts_hj3415/nfs/types.py
contracts_hj3415/universe/__init__.py
contracts_hj3415/universe/constants.py
contracts_hj3415/universe/dto.py
contracts_hj3415/universe/types.py
contracts_hj3415-0.4.0.dist-info/licenses/LICENSE
contracts_hj3415-0.4.0.dist-info/WHEEL
contracts_hj3415-0.4.0.dist-info/METADATA
contracts_hj3415-0.4.0.dist-info/RECORD
