Metadata-Version: 2.4
Name: contracts-hj3415
Version: 0.4.0
Summary: DTO pakages for hj3415
Keywords: example,demo
Author-email: Hyungjin Kim <hj3415@gmail.com>
Requires-Python: >=3.11
Classifier: Programming Language :: Python :: 3
Classifier: License :: OSI Approved :: MIT License
Classifier: Typing :: Typed
License-File: LICENSE
Requires-Dist: pydantic>=2.7
